README.md
setup.py
honeycomb_maze/__init__.py
honeycomb_maze/animal.py
honeycomb_maze/main.py
honeycomb_maze/maze.py
honeycomb_maze/robot.py
honeycomb_maze/static_methods.py
honeycomb_maze.egg-info/PKG-INFO
honeycomb_maze.egg-info/SOURCES.txt
honeycomb_maze.egg-info/dependency_links.txt
honeycomb_maze.egg-info/not-zip-safe
honeycomb_maze.egg-info/requires.txt
honeycomb_maze.egg-info/top_level.txt
honeycomb_maze/integration_testing/__init__.py
honeycomb_maze/integration_testing/curve.py
honeycomb_maze/integration_testing/line.py
honeycomb_maze/integration_testing/not_main.py
honeycomb_maze/integration_testing/triangle.py