Metadata-Version: 2.1
Name: honeycomb-maze
Version: 0.1.1
Summary: Python Implementation of Honeycomb Maze
Home-page: https://github.com/casualcoffeeaddict/Honeycomb-Maze
Author: Alif Ul Aziz
Author-email: alif.aziz@icloud.com
License: MIT
Platform: UNKNOWN
